{"courses":{"MATH4805":{"history":[{"sem":"W","epoch":1618200000,"crn":"34130","course":"MATH4805","source":"12-APR-2021","year":"2021","prof":"Steven  Wang","enrol":"7","type":"Web"}],"name":"Theory of Automata (Honours)","latest":1618200000},"MATH3825":{"latest":1618200000,"history":[{"crn":"34119","course":"MATH3825","source":"12-APR-2021","sem":"W","epoch":1618200000,"enrol":"19","type":"Web","year":"2021","prof":"Steven  Wang"}],"name":"Discrete Structures and Applications"},"MATH4109":{"latest":1651723200,"name":"Fields and Coding Theory (Honours)","history":[{"sem":"F","epoch":1637730000,"crn":"34327","source":"24-NOV-2021","course":"MATH4109","year":"2021","prof":"Steven  Wang","enrol":"14","type":"Web"},{"year":"2022","prof":"Steven  Wang","type":"Web","enrol":"12","sem":"W","epoch":1651723200,"crn":"34327","course":"MATH4109","source":"05-MAY-2022"}]},"MATH3158":{"latest":1651723200,"name":"Rings and Fields (Honours)","history":[{"crn":"13964","course":"MATH3158","source":"24-NOV-2021","sem":"F","epoch":1637730000,"enrol":"9","type":"Web","year":"2021","prof":"Steven  Wang"},{"prof":"Steven  Wang","year":"2022","type":"Web","enrol":"6","epoch":1651723200,"sem":"W","course":"MATH3158","source":"05-MAY-2022","crn":"13964"}]},"MATH3855":{"name":"Discrete Structures and Applications (Honours)","history":[{"year":"2021","prof":"Steven  Wang","enrol":"19","type":"Web","sem":"W","epoch":1618200000,"crn":"34121","source":"12-APR-2021","course":"MATH3855"}],"latest":1618200000},"MATH1104":{"name":"Linear Algebra for Engineering or Science","history":[{"type":"Web","enrol":"234","prof":"Steven  Wang","year":"2021","course":"MATH1104","source":"24-NOV-2021","crn":"13824","epoch":1637730000,"sem":"F"},{"sem":"W","epoch":1651723200,"crn":"13824","source":"05-MAY-2022","course":"MATH1104","year":"2022","prof":"Steven  Wang","type":"Web","enrol":"213"}],"latest":1651723200}},"latest":1651723200,"prof":"Steven  Wang","stats":{"2021-W":45,"2022-W":231,"2021-F":257}}