{"latest":1651723200,"courses":{"MATH4109":{"history":[{"crn":"33911","source":"13-DEC-2018","course":"MATH4109","sem":"F","epoch":1544677200,"type":"Evening","enrol":"12","year":"2018","prof":"Daniel  Panario"},{"prof":"Daniel  Panario","year":"2019","enrol":"12","type":"Evening","epoch":1555387200,"sem":"W","course":"MATH4109","source":"16-APR-2019","crn":"33911"}],"name":"Fields and Coding Theory (Honours)","latest":1555387200},"MATH3855":{"latest":1651723200,"history":[{"source":"24-NOV-2021","course":"MATH3855","crn":"34322","epoch":1637730000,"sem":"F","type":"Web","enrol":"13","prof":"Daniel  Panario","year":"2021"},{"crn":"34322","source":"05-MAY-2022","course":"MATH3855","sem":"W","epoch":1651723200,"enrol":"12","type":"Web","year":"2022","prof":"Daniel  Panario"}],"name":"Discrete Structures and Applications (Honours)"},"MATH3809":{"name":"Introduction to Number Theory and Cryptography","history":[{"year":"2018","prof":"Daniel  Panario","type":"Day","enrol":"8","sem":"F","epoch":1544677200,"crn":"33902","course":"MATH3809","source":"13-DEC-2018"},{"course":"MATH3809","source":"16-APR-2019","crn":"33902","epoch":1555387200,"sem":"W","enrol":"7","type":"Day","prof":"Daniel  Panario","year":"2019"},{"enrol":"13","type":"Web","year":"2021","prof":"Daniel  Panario","crn":"34318","course":"MATH3809","source":"24-NOV-2021","sem":"F","epoch":1637730000},{"year":"2022","prof":"Daniel  Panario","enrol":"12","type":"Web","sem":"W","epoch":1651723200,"crn":"34318","source":"05-MAY-2022","course":"MATH3809"}],"latest":1651723200},"MATH3158":{"latest":1618200000,"name":"Rings and Fields (Honours)","history":[{"crn":"13971","source":"10-JAN-2021","course":"MATH3158","sem":"F","epoch":1610254800,"enrol":"13","type":"Web","year":"2020","prof":"Daniel  Panario"},{"type":"Web","enrol":"13","prof":"Daniel  Panario","year":"2021","course":"MATH3158","source":"12-APR-2021","crn":"13971","epoch":1618200000,"sem":"W"}]},"MATH2108":{"latest":1651723200,"name":"Abstract Algebra I","history":[{"crn":"13945","course":"MATH2108","source":"24-NOV-2021","sem":"F","epoch":1637730000,"enrol":"38","type":"Web","year":"2021","prof":"Daniel  Panario"},{"enrol":"31","type":"Web","year":"2022","prof":"Daniel  Panario","crn":"13945","source":"05-MAY-2022","course":"MATH2108","sem":"W","epoch":1651723200}]},"MATH3101":{"latest":1651723200,"history":[{"prof":"Daniel  Panario","year":"2021","type":"Web","enrol":"38","epoch":1637730000,"sem":"F","source":"24-NOV-2021","course":"MATH3101","crn":"13960"},{"year":"2022","prof":"Daniel  Panario","enrol":"31","type":"Web","sem":"W","epoch":1651723200,"crn":"13960","course":"MATH3101","source":"05-MAY-2022"}],"name":"Algebraic Structures with Computer Applications"},"MATH3825":{"latest":1651723200,"history":[{"sem":"F","epoch":1637730000,"crn":"34320","source":"24-NOV-2021","course":"MATH3825","year":"2021","prof":"Daniel  Panario","enrol":"13","type":"Web"},{"enrol":"12","type":"Web","prof":"Daniel  Panario","year":"2022","source":"05-MAY-2022","course":"MATH3825","crn":"34320","epoch":1651723200,"sem":"W"}],"name":"Discrete Structures and Applications"},"MATH4801":{"latest":1651723200,"history":[{"crn":"13763","source":"13-DEC-2018","course":"MATH4801","sem":"F","epoch":1544677200,"enrol":"7","type":"Evening","year":"2018","prof":"Daniel  Panario"},{"sem":"W","epoch":1555387200,"crn":"13763","source":"16-APR-2019","course":"MATH4801","year":"2019","prof":"Daniel  Panario","type":"Evening","enrol":"7"},{"epoch":1610254800,"sem":"F","source":"10-JAN-2021","course":"MATH4801","crn":"34129","prof":"Daniel  Panario","year":"2020","enrol":"6","type":"Web"},{"crn":"13993","course":"MATH4801","source":"24-NOV-2021","sem":"F","epoch":1637730000,"type":"Web","enrol":"3","year":"2021","prof":"Daniel  Panario"},{"source":"12-APR-2021","course":"MATH4801","crn":"34129","epoch":1618200000,"sem":"W","type":"Web","enrol":"6","prof":"Daniel  Panario","year":"2021"},{"sem":"W","epoch":1651723200,"crn":"13993","source":"05-MAY-2022","course":"MATH4801","year":"2022","prof":"Daniel  Panario","enrol":"3","type":"Web"}],"name":"Topics in Combinatorics (Honours)"}},"stats":{"2020-F":19,"2018-F":27,"2019-W":26,"2021-F":118,"2021-W":19,"2022-W":101},"prof":"Daniel  Panario"}