{"courses":{"MATH3101":{"latest":1513746000,"name":"Algebraic Structures with Computer Applications","history":[{"type":"Day","sem":"F","crn":"13617","enrol":33,"year":"2017","source":"20-DEC-2017","course":"MATH3101","prof":"Goldwyn  Millar","epoch":1513746000}]},"MATH1119":{"history":[{"enrol":88,"year":"2017","crn":"33749","sem":"F","type":"Day","epoch":1513746000,"prof":"Goldwyn  Millar","course":"MATH1119","source":"20-DEC-2017"}],"name":"Linear Algebra: with Applications to Business","latest":1513746000},"MATH2108":{"history":[{"prof":"Goldwyn  Millar","epoch":1513746000,"source":"20-DEC-2017","course":"MATH2108","enrol":33,"year":"2017","sem":"F","type":"Day","crn":"13607"}],"name":"Abstract Algebra I","latest":1513746000}},"stats":{"2017-F":154},"latest":1513746000,"prof":"Goldwyn  Millar"}