{"info":{"desc":"Definite, indefinite integrals. Improper integrals. The fundamental theorem of calculus. An introduction to differential equations. Sequences and series of functions. Power series. Taylor’s formulae. Uniform convergence. An emphasis is placed on proofs and theory.","name":"Calculus and Introductory Analysis II","credit":"0.5"},"latest":1651723200,"enrol_avg":61,"history":[{"year":"2020","prof":"Charles B. Starling","type":"Web","enrol":"61","sem":"F","epoch":1610254800,"crn":"13942","source":"10-JAN-2021","course":"MATH2052"},{"crn":"13933","course":"MATH2052","source":"24-NOV-2021","sem":"F","epoch":1637730000,"type":"Web","enrol":"69","year":"2021","prof":"Charles B. Starling"},{"year":"2021","prof":"Charles B. Starling","type":"Web","enrol":"55","sem":"W","epoch":1618200000,"crn":"13942","course":"MATH2052","source":"12-APR-2021"},{"epoch":1651723200,"sem":"W","course":"MATH2052","source":"05-MAY-2022","crn":"13933","prof":"Charles B. Starling","year":"2022","type":"Web","enrol":"59"}],"profs":[{"count":4,"prof":"Charles B. Starling"}]}