{"info":{"name":"Algebraic Number Theory (Honours)","credit":"0.5","desc":"Algebraic number fields, bases, algebraic integers, integral bases, arithmetic in algebraic number fields, ideal theory, class number."},"profs":[{"count":1,"prof":"Ayse  Alaca"},{"count":6,"prof":"Saban  Alaca"}],"history":[{"prof":"Saban  Alaca","year":"2008","course":"MATH4306","enrol":14,"sem":"F","source":"13-NOV-2008","epoch":1226552400,"type":"Day","crn":"34786"},{"year":"2010","prof":"Saban  Alaca","source":"13-OCT-2010","type":"Day","crn":"34786","epoch":1286942400,"sem":"F","enrol":7,"course":"MATH4306"},{"source":"16-OCT-2013","crn":"13546","type":"Day","epoch":1381896000,"enrol":8,"sem":"F","course":"MATH4306","year":"2013","prof":"Saban  Alaca"},{"year":"2015","prof":"Ayse  Alaca","source":"16-NOV-2015","epoch":1447650000,"type":"Day","crn":"13651","course":"MATH4306","enrol":6,"sem":"F"},{"year":"2017","prof":"Saban  Alaca","epoch":1513746000,"type":"Day","crn":"13659","source":"20-DEC-2017","course":"MATH4306","sem":"F","enrol":2},{"epoch":1576645200,"crn":"13896","type":"Day","source":"18-DEC-2019","course":"MATH4306","sem":"F","enrol":8,"year":"2019","prof":"Saban  Alaca"},{"year":"2021","prof":"Saban  Alaca","epoch":1637730000,"type":"Web","crn":"13991","source":"24-NOV-2021","course":"MATH4306","enrol":10,"sem":"F"}],"enrol_avg":7.85714285714286,"latest":1637730000}